README.rst
setup.py
po2strings/__init__.py
po2strings/po2strings.py
po2strings.egg-info/PKG-INFO
po2strings.egg-info/SOURCES.txt
po2strings.egg-info/dependency_links.txt
po2strings.egg-info/entry_points.txt
po2strings.egg-info/not-zip-safe
po2strings.egg-info/top_level.txt
po2strings/importers/__init__.py
po2strings/importers/android.py
po2strings/importers/android_test.py
po2strings/importers/arb.py
po2strings/importers/arb_test.py
po2strings/importers/ios.py
po2strings/importers/ios_test.py